awq_ext.cp310-win_amd64.pyd
awq_v2_ext.cp310-win_amd64.pyd
exl_ext.cp310-win_amd64.pyd
exlv2_ext.cp310-win_amd64.pyd
autoawq_kernels-0.0.9.dist-info/LICENSE
autoawq_kernels-0.0.9.dist-info/METADATA
autoawq_kernels-0.0.9.dist-info/WHEEL
autoawq_kernels-0.0.9.dist-info/top_level.txt
autoawq_kernels-0.0.9.dist-info/RECORD
