Metadata-Version: 2.1
Name: autoawq_kernels
Version: 0.0.9
Summary: AutoAWQ Kernels implements the AWQ kernels.
Home-page: https://github.com/casper-hansen/AutoAWQ_kernels
Author: Casper Hansen
License: MIT
Keywords: awq,autoawq,quantization,transformers
Platform: linux
Platform: windows
Classifier: Environment :: GPU :: NVIDIA CUDA :: 11.8
Classifier: Environment :: GPU :: NVIDIA CUDA :: 12
Classifier: License :: OSI Approved :: MIT License
Classifier: Natural Language :: English
Classifier: Programming Language :: Python :: 3.8
Classifier: Programming Language :: Python :: 3.9
Classifier: Programming Language :: Python :: 3.10
Classifier: Programming Language :: Python :: 3.11
Classifier: Programming Language :: Python :: 3.12
Classifier: Programming Language :: C++
Requires-Python: >=3.8.0
License-File: LICENSE
Requires-Dist: torch>=2.5.1
